eth_kms_signer/__init__.py
eth_kms_signer/client.py
eth_kms_signer/py.typed
eth_kms_signer/signer.py
eth_kms_signer/utils/__init__.py
eth_kms_signer/utils/address.py
eth_kms_signer/utils/signing.py
tests/__init__.py
tests/test_address_utils.py
tests/test_sign_utils.py
tests/test_signer.py
kms_signer-0.1.1.dist-info/LICENSE
kms_signer-0.1.1.dist-info/METADATA
kms_signer-0.1.1.dist-info/WHEEL
kms_signer-0.1.1.dist-info/top_level.txt
kms_signer-0.1.1.dist-info/RECORD
