Metadata-Version: 2.1
Name: kms-signer
Version: 0.1.1
Summary: KMS signer for Ethereum
Home-page: https://github.com/viswanathkgp12/eth_kms_signer
Author: Viswanath Kapavarapu
Author-email: viswanath.iit@gmail.com
License: MIT
Classifier: Programming Language :: Python :: 3
Classifier: License :: OSI Approved :: MIT License
Classifier: Operating System :: OS Independent
Classifier: Intended Audience :: Developers
Requires-Python: >=3.5
License-File: LICENSE
Requires-Dist: boto3 (<2.0.0,>=1.18.44)
Requires-Dist: py-ecc (<6.0.0,>=5.2.0)
Requires-Dist: ecdsa (<1.0.0,>=0.16.0)
Requires-Dist: eth-account (<1.0.0,>=0.5.5)
